sorsore/__init__.py
sorsore/admin_urls.py
sorsore/apps.py
sorsore/fields.py
sorsore/forms.py
sorsore/importexport.py
sorsore/search_urls.py
sorsore/settings.py
sorsore/urls.py
sorsore/utils.py
sorsore/views.py
sorsore/wagtail_hooks.py
sorsore/widgets.py
sorsore/api/mailchimp.py
sorsore/bin/__init__.py
sorsore/bin/sorsore.py
sorsore/blocks/__init__.py
sorsore/blocks/base_blocks.py
sorsore/blocks/content_blocks.py
sorsore/blocks/html_blocks.py
sorsore/blocks/layout_blocks.py
sorsore/blocks/stream_form_blocks.py
sorsore/blocks/tests/__init__.py
sorsore/blocks/tests/test_blocks.py
sorsore/migrations/0001_initial.py
sorsore/migrations/0002_auto_20180829_1538.py
sorsore/migrations/0003_auto_20180912_1632.py
sorsore/migrations/0004_auto_20181119_1507.py
sorsore/migrations/0005_auto_20181214_2214.py
sorsore/migrations/0006_mailchimpapisettings.py
sorsore/migrations/0007_auto_20190114_1515.py
sorsore/migrations/0008_auto_20190122_1242.py
sorsore/migrations/0009_auto_20190201_1546.py
sorsore/migrations/0010_auto_20190320_1231.py
sorsore/migrations/0010_generalsettings_email.py
sorsore/migrations/0010_remove_generalsettings_robots.py
sorsore/migrations/0011_merge_20190322_1309.py
sorsore/migrations/0012_merge_20190322_1324.py
sorsore/migrations/0013_pagepreview_templates.py
sorsore/migrations/0014_classifiers.py
sorsore/migrations/0015_coderedsessionformsubmission_coderedsubmissionrevision.py
sorsore/migrations/0016_auto_20191025_1620.py
sorsore/migrations/0017_generalsettings_external_new_tab.py
sorsore/migrations/0018_auto_20200805_1702.py
sorsore/migrations/0019_spelling_corrections.py
sorsore/migrations/0020_auto_20210527_1030.py
sorsore/migrations/0021_auto_20210730_1637.py
sorsore/migrations/0022_auto_20210731_1853.py
sorsore/migrations/0023_auto_20210908_1702.py
sorsore/migrations/0024_analyticssettings.py
sorsore/migrations/0025_delete_socialmediasettings.py
sorsore/migrations/0026_auto_20220513_1627.py
sorsore/migrations/0027_auto_20220603_1142.py
sorsore-1.2.0.dev2.dist-info/LICENSE
sorsore-1.2.0.dev2.dist-info/METADATA
sorsore-1.2.0.dev2.dist-info/WHEEL
sorsore-1.2.0.dev2.dist-info/entry_points.txt
sorsore-1.2.0.dev2.dist-info/top_level.txt
sorsore-1.2.0.dev2.dist-info/RECORD
